airflow/providers/email/__init__.py
airflow/providers/email/operators/__init__.py
airflow/providers/email/operators/email.py
airflow/providers/email/utils/__init__.py
airflow/providers/email/utils/email.py
apache_airflow_backport_providers_smtp-2021.6.24.dist-info/LICENSE
apache_airflow_backport_providers_smtp-2021.6.24.dist-info/LICENSE-bootstrap-toggle.txt
apache_airflow_backport_providers_smtp-2021.6.24.dist-info/LICENSE-bootstrap.txt
apache_airflow_backport_providers_smtp-2021.6.24.dist-info/LICENSE-bootstrap3-typeahead.txt
apache_airflow_backport_providers_smtp-2021.6.24.dist-info/LICENSE-d3-tip.txt
apache_airflow_backport_providers_smtp-2021.6.24.dist-info/LICENSE-d3js.txt
apache_airflow_backport_providers_smtp-2021.6.24.dist-info/LICENSE-dagre-d3.txt
apache_airflow_backport_providers_smtp-2021.6.24.dist-info/LICENSE-datatables.txt
apache_airflow_backport_providers_smtp-2021.6.24.dist-info/LICENSE-elasticmock.txt
apache_airflow_backport_providers_smtp-2021.6.24.dist-info/LICENSE-eonasdan-bootstrap-datetimepicker.txt
apache_airflow_backport_providers_smtp-2021.6.24.dist-info/LICENSE-flask-kerberos.txt
apache_airflow_backport_providers_smtp-2021.6.24.dist-info/LICENSE-hue.txt
apache_airflow_backport_providers_smtp-2021.6.24.dist-info/LICENSE-jqclock.txt
apache_airflow_backport_providers_smtp-2021.6.24.dist-info/LICENSE-jquery.txt
apache_airflow_backport_providers_smtp-2021.6.24.dist-info/LICENSE-moment-strftime.txt
apache_airflow_backport_providers_smtp-2021.6.24.dist-info/LICENSE-moment.txt
apache_airflow_backport_providers_smtp-2021.6.24.dist-info/LICENSE-normalize.txt
apache_airflow_backport_providers_smtp-2021.6.24.dist-info/LICENSE-python-nvd3.txt
apache_airflow_backport_providers_smtp-2021.6.24.dist-info/LICENSE-python-slugify.txt
apache_airflow_backport_providers_smtp-2021.6.24.dist-info/METADATA
apache_airflow_backport_providers_smtp-2021.6.24.dist-info/NOTICE
apache_airflow_backport_providers_smtp-2021.6.24.dist-info/WHEEL
apache_airflow_backport_providers_smtp-2021.6.24.dist-info/top_level.txt
apache_airflow_backport_providers_smtp-2021.6.24.dist-info/RECORD
